yapb-0.0.13.dist-info/METADATA
yapb-0.0.13.dist-info/WHEEL
yapb-0.0.13.dist-info/license_files/LICENSE
yapb/__init__.py
yapb/yapb.pyi
yapb/py.typed
yapb/yapb.cpython-312-darwin.so
yapb-0.0.13.dist-info/RECORD
