Metadata-Version: 2.1
Name: yapb
Version: 0.0.13
Classifier: Programming Language :: Python
Classifier: Programming Language :: Rust
Classifier: Programming Language :: Python :: Implementation :: CPython
Classifier: Programming Language :: Python :: Implementation :: PyPy
Requires-Dist: black; extra == 'dev'
Requires-Dist: bumpver; extra == 'dev'
Requires-Dist: mypy; extra == 'dev'
Requires-Dist: ruff; extra == 'dev'
Requires-Dist: pytest; extra == 'dev'
Requires-Dist: pre-commit; extra == 'dev'
Provides-Extra: dev
License-File: LICENSE
Summary: A Minimalist Progress Bar for Python
Keywords: progress,bar,progressbar,progress-bar
Author: Wilhelm Söderkvist Vermelin
Author-email: wilhelm.wermelin@icloud.com
Maintainer-email: Wilhelm Söderkvist Vermelin <wilhelm.wermelin@icloud.com>
Requires-Python: >=3.7
Project-URL: repository, https://github.com/wilswer/yapb
